api_go/__init__.py
api_go/client.py
api_go/decorators.py
api_go/exceptions.py
api_go/utils.py
api_go_client-0.1.0.dist-info/METADATA
api_go_client-0.1.0.dist-info/WHEEL
api_go_client-0.1.0.dist-info/top_level.txt
api_go_client-0.1.0.dist-info/RECORD
