Metadata-Version: 2.4
Name: api-go-client
Version: 0.1.0
Requires-Python: >=3.7
Requires-Dist: requests>=2.28.0
Dynamic: requires-dist
Dynamic: requires-python
